setup.cfg
setup.py
PreForM/PreForM.py
PreForM/__init__.py
PreForM/__main__.py
PreForM.py.egg-info/PKG-INFO
PreForM.py.egg-info/SOURCES.txt
PreForM.py.egg-info/dependency_links.txt
PreForM.py.egg-info/entry_points.txt
PreForM.py.egg-info/pbr.json
PreForM.py.egg-info/requires.txt
PreForM.py.egg-info/top_level.txt