Metadata-Version: 1.1
Name: PreForM.py
Version: 1.1.3
Summary: PreForM.py, Preprocessor for Fortran poor Men
Home-page: https://github.com/szaghi/PreForM
Author: Stefano Zaghi
Author-email: stefano.zaghi@gmail.com
License: UNKNOWN
Platform: UNKNOWN
Classifier: Development Status :: 5 - Production/Stable
Classifier: License :: OSI Approved :: GNU General Public License v3 (GPLv3)
Classifier: Programming Language :: Python
Classifier: Programming Language :: Python :: 2.7
Classifier: Programming Language :: Python :: 3.4
Classifier: Environment :: Console
Classifier: Intended Audience :: Developers
Classifier: Topic :: Software Development :: Code Generators
